<?xml version="1.0" encoding="UTF-8"?>
<objects serializationModel="Studio.02.02.00">
	<object class="AudioFile" id="{d8d9d55f-6e1c-47e2-81b0-632b4b42f037}">
		<property name="assetPath">
			<value>UI/UI_Dialogue_box_open-002.ogg</value>
		</property>
		<property name="frequencyInKHz">
			<value>44.0999985</value>
		</property>
		<property name="channelCount">
			<value>2</value>
		</property>
		<property name="length">
			<value>0.64249433106575959</value>
		</property>
		<relationship name="masterAssetFolder">
			<destination>{e047f6fd-9ef0-41e4-8ae7-06d70d02201a}</destination>
		</relationship>
	</object>
</objects>
